Metadata-Version: 1.1
Name: app-rim
Version: 0.0.1
Summary: Application Runtime Image Manager
Home-page: https://github.com/jbytecoder/app-rim
Author: jbytecoder
Author-email: jbytecoder@gmail.com
License: UNKNOWN
Platform: UNKNOWN
Classifier: Programming Language :: Python :: 3.6
Classifier: License :: OSI Approved :: MIT License
Classifier: Operating System :: POSIX :: Linux
